collapsar/BelongsTo.py
collapsar/Boolean.py
collapsar/Calendar.py
collapsar/CollapsarRequest.py
collapsar/CustomField.py
collapsar/Field.py
collapsar/Id.py
collapsar/Image.py
collapsar/Markdown.py
collapsar/Password.py
collapsar/Resource.py
collapsar/RichText.py
collapsar/Select.py
collapsar/TextInput.py
collapsar/__init__.py
collapsar/commands/CollapsarInstallCommand.py
collapsar/commands/MakeResourceCommand.py
collapsar/commands/UserAddCommand.py
collapsar/config/__init__.py
collapsar/config/collapsar.py
collapsar/config/filesystem.py
collapsar/controllers/AuthController.py
collapsar/controllers/CollapsarController.py
collapsar/controllers/FieldsController.py
collapsar/controllers/ResourceDeleteController.py
collapsar/controllers/ResourceIndexController.py
collapsar/controllers/ResourceShowController.py
collapsar/controllers/ResourceStoreController.py
collapsar/controllers/ResourceUpdateController.py
collapsar/controllers/__init__.py
collapsar/dist/assets/app-bundle.umd.js
collapsar/dist/assets/manifest.json
collapsar/dist/assets/style.css
collapsar/foundation/Collapsar.py
collapsar/foundation/__init__.py
collapsar/helpers/DashboardHelper.py
collapsar/helpers/__init__.py
collapsar/middlewares/__init__.py
collapsar/providers/CollapsarApplicationProvider.py
collapsar/providers/CollapsarProvider.py
collapsar/providers/__init__.py
collapsar/routes/__init__.py
collapsar/routes/api.py
collapsar/routes/web.py
collapsar/stubs/Resource.py
collapsar/templates/admin/base.html
collapsar/templates/admin/index.html
collapsar/traits/FillsFields.py
collapsar/traits/ForwardsCalls.py
collapsar/traits/RelationField.py
collapsar/traits/ResolvesFields.py
collapsar/traits/__init__.py
collapsar-0.1.1.dist-info/LICENSE
collapsar-0.1.1.dist-info/METADATA
collapsar-0.1.1.dist-info/WHEEL
collapsar-0.1.1.dist-info/top_level.txt
collapsar-0.1.1.dist-info/RECORD
