Metadata-Version: 2.1
Name: collapsar
Version: 0.1.1
Summary: Create beautiful admin dashboards in Masonite Framework
Home-page: https://github.com/usecollapsar/collapsar
Author: Eduardo Aguad
Author-email: eduardo@aguad.dev
License: MIT license
Keywords: Masonite,Python,Development
Classifier: Development Status :: 3 - Alpha
Classifier: Intended Audience :: Developers
Classifier: Topic :: Software Development :: Build Tools
Classifier: Environment :: Web Environment
Classifier: License :: OSI Approved :: MIT License
Classifier: Operating System :: OS Independent
Classifier: Programming Language :: Python :: 3.6
Classifier: Programming Language :: Python :: 3.7
Classifier: Programming Language :: Python :: 3.8
Classifier: Programming Language :: Python :: 3.9
Classifier: Topic :: Internet :: WWW/HTTP
Classifier: Topic :: Internet :: WWW/HTTP :: Dynamic Content
Classifier: Topic :: Internet :: WWW/HTTP :: WSGI
Classifier: Topic :: Software Development :: Libraries :: Application Frameworks
Classifier: Topic :: Software Development :: Libraries :: Python Modules
Classifier: Framework :: Masonite
License-File: LICENSE
Requires-Dist: masonite <5.0,>=4.0
Requires-Dist: masonite <5,>=4
Requires-Dist: masonite-orm <3,>=2
Requires-Dist: attrs >=23
Requires-Dist: requests >=2.31
Requires-Dist: python-slugify >=8
Provides-Extra: dev
Requires-Dist: black ; extra == 'dev'
Requires-Dist: flake8 ; extra == 'dev'
Requires-Dist: coverage ; extra == 'dev'
Requires-Dist: pytest ; extra == 'dev'
Requires-Dist: pytest-cov ; extra == 'dev'
Requires-Dist: twine >=1.5.0 ; extra == 'dev'
Requires-Dist: wheel ; extra == 'dev'
Requires-Dist: pytest-dotenv ; extra == 'dev'
